{
	"info": {
		"_postman_id": "ce9b55a3-9c24-4ca8-bf97-8651b20fd9b0",
		"name": "Counsellor",
		"schema": "https://schema.getpostman.com/json/collection/v2.1.0/collection.json",
		"_exporter_id": "26813740"
	},
	"item": [
		{
			"name": "add",
			"request": {
				"method": "POST",
				"header": [],
				"body": {
					"mode": "raw",
					"raw": "{\r\n    \"name\" : \"asad three\",\r\n    \"email\" : \"asad_counsellor_3@gmail.com\",\r\n    \"password\" : \"Test@12345\"\r\n}",
					"options": {
						"raw": {
							"language": "json"
						}
					}
				},
				"url": {
					"raw": "http://127.0.0.1:8000/counsellor/add/",
					"protocol": "http",
					"host": [
						"127",
						"0",
						"0",
						"1"
					],
					"port": "8000",
					"path": [
						"counsellor",
						"add",
						""
					]
				}
			},
			"response": []
		},
		{
			"name": "update",
			"request": {
				"method": "PUT",
				"header": [],
				"body": {
					"mode": "raw",
					"raw": "{\r\n    \"name\" : \"asad change\",\r\n    \"email\" : \"asad_patient@gmail.com\",\r\n    \"password\" : \"Test@12345\"\r\n}",
					"options": {
						"raw": {
							"language": "json"
						}
					}
				},
				"url": {
					"raw": "http://127.0.0.1:8000/paticounsellorent/update/?id =2",
					"protocol": "http",
					"host": [
						"127",
						"0",
						"0",
						"1"
					],
					"port": "8000",
					"path": [
						"paticounsellorent",
						"update",
						""
					],
					"query": [
						{
							"key": "id ",
							"value": "2"
						}
					]
				}
			},
			"response": []
		},
		{
			"name": "list",
			"request": {
				"method": "GET",
				"header": [],
				"url": {
					"raw": "http://127.0.0.1:8000/counsellor/lists/?is_active=1",
					"protocol": "http",
					"host": [
						"127",
						"0",
						"0",
						"1"
					],
					"port": "8000",
					"path": [
						"counsellor",
						"lists",
						""
					],
					"query": [
						{
							"key": "is_active",
							"value": "1"
						}
					]
				}
			},
			"response": []
		},
		{
			"name": "delete",
			"request": {
				"method": "DELETE",
				"header": [],
				"url": {
					"raw": "http://127.0.0.1:8000/counsellor/delete/?email=naseer.shoaib92@gmail.com&id=1",
					"protocol": "http",
					"host": [
						"127",
						"0",
						"0",
						"1"
					],
					"port": "8000",
					"path": [
						"counsellor",
						"delete",
						""
					],
					"query": [
						{
							"key": "email",
							"value": "naseer.shoaib92@gmail.com"
						},
						{
							"key": "id",
							"value": "1"
						}
					]
				}
			},
			"response": []
		}
	]
}